{
  "city": "河北邯郸",
  "updateTime": "2026-07-17 16:35",
  "today": {
    "date": "2026-07-17",
    "week": "星期五",
    "weather": "阵雨",
    "weatherCode": "81",
    "tempMax": 28,
    "tempMin": 20,
    "humidity": 61,
    "windDir": "东北风",
    "windScale": "2级",
    "windSpeed": 6,
    "pressure": 1001,
    "visibility": 9.5,
    "sunrise": "05:16",
    "sunset": "19:39",
    "uv": "中等",
    "aqi": 130,
    "aqiLevel": "轻度污染",
    "feelsLike": 31
  },
  "forecast": [
    {
      "date": "2026-07-18",
      "week": "星期六",
      "weather": "阴",
      "weatherCode": "3",
      "tempMax": 31,
      "tempMin": 22
    },
    {
      "date": "2026-07-19",
      "week": "星期日",
      "weather": "多云",
      "weatherCode": "2",
      "tempMax": 34,
      "tempMin": 24
    },
    {
      "date": "2026-07-20",
      "week": "星期一",
      "weather": "小毛毛雨",
      "weatherCode": "51",
      "tempMax": 35,
      "tempMin": 25
    },
    {
      "date": "2026-07-21",
      "week": "星期二",
      "weather": "雷阵雨",
      "weatherCode": "95",
      "tempMax": 37,
      "tempMin": 24
    },
    {
      "date": "2026-07-22",
      "week": "星期三",
      "weather": "小毛毛雨",
      "weatherCode": "51",
      "tempMax": 38,
      "tempMin": 24
    }
  ]
}