{
  "city": "河北邯郸",
  "updateTime": "2026-07-18 19:11",
  "today": {
    "date": "2026-07-18",
    "week": "星期六",
    "weather": "大毛毛雨",
    "weatherCode": "55",
    "tempMax": 30,
    "tempMin": 22,
    "humidity": 90,
    "windDir": "南风",
    "windScale": "2级",
    "windSpeed": 8,
    "pressure": 1001,
    "visibility": 5.5,
    "sunrise": "05:17",
    "sunset": "19:39",
    "uv": "强",
    "aqi": 130,
    "aqiLevel": "轻度污染",
    "feelsLike": 34
  },
  "forecast": [
    {
      "date": "2026-07-19",
      "week": "星期日",
      "weather": "阴",
      "weatherCode": "3",
      "tempMax": 33,
      "tempMin": 24
    },
    {
      "date": "2026-07-20",
      "week": "星期一",
      "weather": "小毛毛雨",
      "weatherCode": "51",
      "tempMax": 33,
      "tempMin": 24
    },
    {
      "date": "2026-07-21",
      "week": "星期二",
      "weather": "阴",
      "weatherCode": "3",
      "tempMax": 36,
      "tempMin": 25
    },
    {
      "date": "2026-07-22",
      "week": "星期三",
      "weather": "小毛毛雨",
      "weatherCode": "51",
      "tempMax": 36,
      "tempMin": 27
    },
    {
      "date": "2026-07-23",
      "week": "星期四",
      "weather": "雷阵雨",
      "weatherCode": "95",
      "tempMax": 34,
      "tempMin": 24
    }
  ]
}